secondguard/__init__.py
secondguard/main.py
secondguard/pyca.py
secondguard/secondguard.py
secondguard/testing_utils.py
secondguard/utils.py
tests/__init__.py
tests/test_client.py
tests/test_pyca.py
tests/test_utils.py
tests/testing_utils.py
tests/utils.py
secondguard-2.5.1.dist-info/LICENSE
secondguard-2.5.1.dist-info/METADATA
secondguard-2.5.1.dist-info/WHEEL
secondguard-2.5.1.dist-info/top_level.txt
secondguard-2.5.1.dist-info/RECORD
