Metadata-Version: 2.1
Name: secondguard
Version: 2.5.1
Summary: SecondGuard Python Library
Home-page: https://github.com/secondguard/secondguard-python/
Author: Michael Flaxman
Author-email: python-library@secondguard.com
License: UNKNOWN
Platform: UNKNOWN
Classifier: Programming Language :: Python :: 3
Classifier: License :: OSI Approved :: MIT License
Classifier: Operating System :: OS Independent
Requires-Python: >=3.3
Requires-Dist: cryptography (==2.9.2)
Requires-Dist: pytest
Requires-Dist: requests
